<?xml version="1.0" encoding="UTF-8"?>
<cinema>

    <utilisateurs>
        <utilisateur id="U1">
            <nom>Vincent Moule</nom>
            <email>vincent.moule@gmail.com</email>
            <tel>+212-684-989-567</tel>
            <carte-credit>1234-5689-8532-6955</carte-credit>
        </utilisateur>
        
        
        <utilisateur id="U21">
            <nom>Aymen</nom>
            <email>aymen@gmail.com</email>
            <tel>+212-236-458-896</tel>
            <carte-credit>1234-5689-8532-6955 3</carte-credit>
        </utilisateur>
    </utilisateurs>


    <films>

        <film id="F1" anne="2014">

            <titre>Whiplash</titre>
            <genre>Drame</genre>
            <realisateur>Damien Chazelle</realisateur>
            <duree>1h46m</duree>
            <poster source="../../posters/F21.jpg"/>
        </film>
        <film id="F2" anne="2014">

            <titre>Whiplash</titre>
            <genre>science</genre>
            <realisateur>Damien Chazelle</realisateur>
            <duree>1h46m</duree>
            <poster source="../../posters/F21.jpg"/>
        </film>

        <film id="F3" anne="2014">

            <titre>Whiplash 2</titre>
            <genre>action</genre>
            <realisateur>Damien Chazelle</realisateur>
            <duree>1h46m</duree>
            <poster source="../../posters/F21.jpg"/>
        </film>
        <film id="F4" annee="1334">
            <titre>test</titre>
            <genre>action</genre>
            <realisateur>test</realisateur>
            <duree>30</duree>
            <poster source="src/views/posters/1.PNG"/>
            <description>retsts</description>
        </film>
        <film id="F5" annee="1334">
            <titre>test</titre>
            <genre>drame</genre>
            <realisateur>test</realisateur>
            <duree>30</duree>
            <poster source="src/views/posters/1.PNG"/>
            <description>retsts</description>
        </film>
        <film id="F6" annee="30">
            <titre>y</titre>
            <genre>drame</genre>
            <realisateur>y</realisateur>
            <duree>30</duree>
            <poster source="src/views/posters/1.PNG"/>
            <description>hhs</description>
        </film>
   </films>

    <salles>
        <salle id="S1" capacite="70"/>
        <salle id="S2" capacite="80"/>
        <salle id="S3" capacite="120"/>
        <salle id="S4" capacite="90"/>
    <salle id="S5" capacite="100"/></salles>

    <sieges>
        <siege id="SI889">
            <salle>S08</salle>
            <rang>7</rang>
            <numero>44</numero>
        </siege>
        <siege id="S89">
            <salle>S08</salle>
            <rang>7</rang>
            <numero>44</numero>
        </siege>
    </sieges>

    <seances>
        <seance id="S659">
            <date>06/11/2021</date>
            <heure>18h45m</heure>
            <film>F1</film>
            <salle>S08</salle>
            <prix>60</prix>
        </seance>
        <seance id="S658">
            <date>06/11/2021</date>
            <heure>18h45m</heure>
            <film>F2</film>
            <salle>S08</salle>
            <prix>60</prix>
        </seance>

    </seances>

    <reservations>
        <reservation code="R-215-487">
            <date>01/11/2021</date>
            <heure>23h02m</heure>
            <utilisateur>U1</utilisateur>
            <siege>SI889</siege>
            <seance>SE658</seance>
        </reservation>
        <reservation code="487">
            <date>01/11/2021</date>
            <heure>23h02m</heure>
            <utilisateur>U1</utilisateur>
            <siege>SI889</siege>
            <seance>SE658</seance>
        </reservation>
        <reservation code="47">
            <date>01/11/2021</date>
            <heure>23h02m</heure>
            <utilisateur>U1</utilisateur>
            <siege>SI889</siege>
            <seance>SE658</seance>
        </reservation>
        
        

    </reservations>


</cinema>
